pymdp/__init__.py
pymdp/mdp.py
pymdp/mdp_solver.py
pymdp/tests/__init__.py
pymdp/tests/test_mdp.py
pymdp-0.0.1.dist-info/LICENSE
pymdp-0.0.1.dist-info/METADATA
pymdp-0.0.1.dist-info/WHEEL
pymdp-0.0.1.dist-info/top_level.txt
pymdp-0.0.1.dist-info/RECORD
